fxdatapi/__init__.py
fxdatapi/auth.py
fxdatapi/convert.py
fxdatapi/convert_all.py
fxdatapi/currencies.py
fxdatapi/daily_average.py
fxdatapi/historical.py
fxdatapi/margins_spreads.py
fxdatapi/monthly_average.py
fxdatapi/performances.py
fxdatapi/signals.py
fxdatapi/version.py
fxdatapi/weekly_average.py
fxdatapi-1.1.4.dist-info/LICENSE
fxdatapi-1.1.4.dist-info/METADATA
fxdatapi-1.1.4.dist-info/WHEEL
fxdatapi-1.1.4.dist-info/top_level.txt
fxdatapi-1.1.4.dist-info/RECORD
