Metadata-Version: 2.1
Name: fxdatapi
Version: 1.1.4
Summary: Python library for integrating with the Currency API.
Home-page: https://horisystems.com/currency-api/
Author: Hori Systems Limited
Author-email: support@horisystems.com
License: BSD 3-Clause
Project-URL: Bug Tracker, https://github.com/horisystems/fxdatapi_sdk/issues
Project-URL: Changes, https://github.com/horisystems/fxdatapi_sdk/blob/main/CHANGELOG.md
Project-URL: Documentation, https://docs.fxdatapi.com/
Project-URL: Source Code, https://github.com/horisystems/fxdatapi_sdk
Keywords: currency,currency api,fxdatapi,fxdatapi sdk,rate,rates,exchange rates,hori,horisystems,hori systems
Classifier: Development Status :: 5 - Production/Stable
Classifier: Intended Audience :: Developers
Classifier: License :: OSI Approved :: BSD License
Classifier: Operating System :: OS Independent
Classifier: Programming Language :: Python
Classifier: Programming Language :: Python :: 2
Classifier: Programming Language :: Python :: 2.7
Classifier: Programming Language :: Python :: 3
Classifier: Programming Language :: Python :: 3.4
Classifier: Programming Language :: Python :: 3.5
Classifier: Programming Language :: Python :: 3.6
Classifier: Programming Language :: Python :: 3.7
Classifier: Programming Language :: Python :: 3.8
Classifier: Programming Language :: Python :: 3.9
Classifier: Programming Language :: Python :: 3.10
Classifier: Programming Language :: Python :: Implementation :: PyPy
Classifier: Topic :: Software Development :: Libraries :: Python Modules
Requires-Python: >=2.7, !=3.0.*, !=3.1.*, !=3.2.*, !=3.3.*
License-File: LICENSE
Requires-Dist: requests
